Workbook
Name CriteriosConsultaProduto: 'Quadro de Resumo'!$AM$7:$AM$8
Name Lista_Produtos: TB_Produtos[[#All],[Produto]]

Sheet Dashboard
B1: DASHBOARD
AF2: FATURAMENTO | AX2: DESPESAS | BP2: LUCRO
AF4: =SUM(TB_Saídas[Valor de Venda]) -> 19042.5 | AX4: =SUM(TB_Entradas[Valor da Compra]) -> 5530 | BP4: =(AF4-AX4)/AX4 -> 2.4434901
C8: TOP 5 PRODUTOS MAIS VENDIDOS
AB9: FATURAMENTO X DESPESA
AB28: ENTRADA X SAÍDA MENSAL | BP28: ENTRADA X SAÍDA ANUAL
C29: RANKING FATURAMENTO
AN30: Café
C31: 1º | G31: ='Base de Cálculos'!B11 -> Café | Q31: ='Base de Cálculos'!C11 -> 5670
C34: 2º | G34: ='Base de Cálculos'!B12 -> Chocolate Quente | Q34: ='Base de Cálculos'!C12 -> 4250
C37: 3º | G37: ='Base de Cálculos'!B13 -> Pão de Queijo | Q37: ='Base de Cálculos'!C13 -> 3000
C40: 4º | G40: ='Base de Cálculos'!B14 -> Refrigerante | Q40: ='Base de Cálculos'!C14 -> 1680
C43: 5º | G43: ='Base de Cálculos'!B15 -> Coxinha | Q43: ='Base de Cálculos'!C15 -> 1592.5

Sheet Produtos
D1: Cadastro de Produtos
B4: Produto | C4: Unidade de Medida | D4: Estoque Mínimo | E4: Custo Unitário | F4: Preço Unitário
B5: Café | C5: Unidade | D5: 50 | E5: 2 | F5: 6
B6: Pão | C6: Kg | D6: 5 | E6: 1.5 | F6: 3
B7: Coxinha | C7: Kg | D7: 50 | E7: 0.5 | F7: 6.5
B8: Esfiha | C8: Kg | D8: 50 | E8: 1 | F8: 4.5
B9: Risoles | C9: Kg | D9: 50 | E9: 1 | F9: 4
B10: Empada | C10: Kg | D10: 50 | E10: 1 | F10: 4
B11: Quibe | C11: Kg | D11: 50 | E11: 0.5 | F11: 4
B12: Chá | C12: Unidade | D12: 15 | E12: 0.5 | F12: 2
B13: Manteiga | C13: Unidade | D13: 15 | E13: 0.25 | F13: 1
B14: Requeijão | C14: Unidade | D14: 15 | E14: 0.25 | F14: 1
B15: Chocolate Quente | C15: Caixa | D15: 10 | E15: 0.25 | F15: 8.5
B16: Leite | C16: Caixa | D16: 12 | E16: 10 | F16: 5
... B31: Enroladinho | C31: Kg | D31: 10 | E31: 0.25 | F31: 5

Sheet Fornecedor
E1: Cadastro de Fornecedor
B4: Empresa | C4: Telefone | D4: Responsável | E4: E-mail
B5: Mercado Express | C5: (11) 1122-4422 | D5: Maria | E5: maria@mercadoexpress.com.br
B6: Frigorífico Z | C6: (11) 1001-2022 | D6: Carlos | E6: carlos@frigoríficoz.com.br
B7: Distribuídora KS | C7: (11) 1300-4033 | D7: Eduardo | E7: eduardo@distribuídoraks.com.br
B8: Salgados Gran | C8: (11) 1400-3022 | D8: Claudia | E8: claudia@salgadosgran.com.br

Sheet Entradas
F1: Controle de Entradas
B4: Mês | C4: Data | D4: Produto | E4: Fornecedor | F4: Quantidade Comprada | G4: Custo Unitário | H4: Valor da Compra
B5: =MONTH(TB_Entradas[[#This Row],[Data]]) -> 1 | C5: 44566 | D5: Café | E5: Mercado Express | F5: 100 | G5: {=_xlfn.XLOOKUP(TB_Entradas[[#This Row],[Produto]],TB_Produtos[[#All],[Produto]],TB_Produtos[[#All],[Custo Unitário]],"Produto não Encontrado",0,1)} -> 2 | H5: =IFERROR(TB_Entradas[[#This Row],[Quantidade Comprada]]*TB_Entradas[[#This Row],[Custo Unitário]],"Erro ao calcular") -> 200
B6: =MONTH(TB_Entradas[[#This Row],[Data]]) -> 1 | C6: 44566 | D6: Coxinha | E6: Salgados Gran | F6: 100 | G6: {=_xlfn.XLOOKUP(TB_Entradas[[#This Row],[Produto]],TB_Produtos[[#All],[Produto]],TB_Produtos[[#All],[Custo Unitário]],"Produto não Encontrado",0,1)} -> 0.5 | H6: =IFERROR(TB_Entradas[[#This Row],[Quantidade Comprada]]*TB_Entradas[[#This Row],[Custo Unitário]],"Erro ao calcular") -> 50
B7: =MONTH(TB_Entradas[[#This Row],[Data]]) -> 1 | C7: 44576 | D7: Chocolate Quente | E7: Mercado Express | F7: 90 | G7: {=_xlfn.XLOOKUP(TB_Entradas[[#This Row],[Produto]],TB_Produtos[[#All],[Produto]],TB_Produtos[[#All],[Custo Unitário]],"Produto não Encontrado",0,1)} -> 0.25 | H7: =IFERROR(TB_Entradas[[#This Row],[Quantidade Comprada]]*TB_Entradas[[#This Row],[Custo Unitário]],"Erro ao calcular") -> 22.5
B8: =MONTH(TB_Entradas[[#This Row],[Data]]) -> 1 | C8: 44578 | D8: Pão de Queijo | E8: Salgados Gran | F8: 100 | G8: {=_xlfn.XLOOKUP(TB_Entradas[[#This Row],[Produto]],TB_Produtos[[#All],[Produto]],TB_Produtos[[#All],[Custo Unitário]],"Produto não Encontrado",0,1)} -> 0.25 | H8: =IFERROR(TB_Entradas[[#This Row],[Quantidade Comprada]]*TB_Entradas[[#This Row],[Custo Unitário]],"Erro ao calcular") -> 25
B9: =MONTH(TB_Entradas[[#This Row],[Data]]) -> 2 | C9: 44593 | D9: Pão de Queijo | E9: Salgados Gran | F9: 85 | G9: {=_xlfn.XLOOKUP(TB_Entradas[[#This Row],[Produto]],TB_Produtos[[#All],[Produto]],TB_Produtos[[#All],[Custo Unitário]],"Produto não Encontrado",0,1)} -> 0.25 | H9: =IFERROR(TB_Entradas[[#This Row],[Quantidade Comprada]]*TB_Entradas[[#This Row],[Custo Unitário]],"Erro ao calcular") -> 21.25
B10: =MONTH(TB_Entradas[[#This Row],[Data]]) -> 2 | C10: 44594 | D10: Chocolate Quente | E10: Mercado Express | F10: 80 | G10: {=_xlfn.XLOOKUP(TB_Entradas[[#This Row],[Produto]],TB_Produtos[[#All],[Produto]],TB_Produtos[[#All],[Custo Unitário]],"Produto não Encontrado",0,1)} -> 0.25 | H10: =IFERROR(TB_Entradas[[#This Row],[Quantidade Comprada]]*TB_Entradas[[#This Row],[Custo Unitário]],"Erro ao calcular") -> 20
B11: =MONTH(TB_Entradas[[#This Row],[Data]]) -> 2 | C11: 44598 | D11: Café | E11: Mercado Express | F11: 125 | G11: {=_xlfn.XLOOKUP(TB_Entradas[[#This Row],[Produto]],TB_Produtos[[#All],[Produto]],TB_Produtos[[#All],[Custo Unitário]],"Produto não Encontrado",0,1)} -> 2 | H11: =IFERROR(TB_Entradas[[#This Row],[Quantidade Comprada]]*TB_Entradas[[#This Row],[Custo Unitário]],"Erro ao calcular") -> 250
B12: =MONTH(TB_Entradas[[#This Row],[Data]]) -> 2 | C12: 44602 | D12: Cerveja | E12: Distribuídora KS | F12: 50 | G12: {=_xlfn.XLOOKUP(TB_Entradas[[#This Row],[Produto]],TB_Produtos[[#All],[Produto]],TB_Produtos[[#All],[Custo Unitário]],"Produto não Encontrado",0,1)} -> 0.75 | H12: =IFERROR(TB_Entradas[[#This Row],[Quantidade Comprada]]*TB_Entradas[[#This Row],[Custo Unitário]],"Erro ao calcular") -> 37.5
B13: =MONTH(TB_Entradas[[#This Row],[Data]]) -> 2 | C13: 44612 | D13: Coxinha | E13: Salgados Gran | F13: 100 | G13: {=_xlfn.XLOOKUP(TB_Entradas[[#This Row],[Produto]],TB_Produtos[[#All],[Produto]],TB_Produtos[[#All],[Custo Unitário]],"Produto não Encontrado",0,1)} -> 0.5 | H13: =IFERROR(TB_Entradas[[#This Row],[Quantidade Comprada]]*TB_Entradas[[#This Row],[Custo Unitário]],"Erro ao calcular") -> 50
B14: =MONTH(TB_Entradas[[#This Row],[Data]]) -> 3 | C14: 44625 | D14: Refrigerante | E14: Distribuídora KS | F14: 250 | G14: {=_xlfn.XLOOKUP(TB_Entradas[[#This Row],[Produto]],TB_Produtos[[#All],[Produto]],TB_Produtos[[#All],[Custo Unitário]],"Produto não Encontrado",0,1)} -> 2 | H14: =IFERROR(TB_Entradas[[#This Row],[Quantidade Comprada]]*TB_Entradas[[#This Row],[Custo Unitário]],"Erro ao calcular") -> 500
B15: =MONTH(TB_Entradas[[#This Row],[Data]]) -> 3 | C15: 44630 | D15: Pão de Queijo | E15: Salgados Gran | F15: 50 | G15: {=_xlfn.XLOOKUP(TB_Entradas[[#This Row],[Produto]],TB_Produtos[[#All],[Produto]],TB_Produtos[[#All],[Custo Unitário]],"Produto não Encontrado",0,1)} -> 0.25 | H15: =IFERROR(TB_Entradas[[#This Row],[Quantidade Comprada]]*TB_Entradas[[#This Row],[Custo Unitário]],"Erro ao calcular") -> 12.5
B16: =MONTH(TB_Entradas[[#This Row],[Data]]) -> 3 | C16: 44635 | D16: Café | E16: Mercado Express | F16: 150 | G16: {=_xlfn.XLOOKUP(TB_Entradas[[#This Row],[Produto]],TB_Produtos[[#All],[Produto]],TB_Produtos[[#All],[Custo Unitário]],"Produto não Encontrado",0,1)} -> 2 | H16: =IFERROR(TB_Entradas[[#This Row],[Quantidade Comprada]]*TB_Entradas[[#This Row],[Custo Unitário]],"Erro ao calcular") -> 300
... B58: =MONTH(TB_Entradas[[#This Row],[Data]]) -> 12 | C58: 44910 | D58: Chocolate Quente | E58: Mercado Express | F58: 40 | G58: {=_xlfn.XLOOKUP(TB_Entradas[[#This Row],[Produto]],TB_Produtos[[#All],[Produto]],TB_Produtos[[#All],[Custo Unitário]],"Produto não Encontrado",0,1)} -> 0.25 | H58: =IFERROR(TB_Entradas[[#This Row],[Quantidade Comprada]]*TB_Entradas[[#This Row],[Custo Unitário]],"Erro ao calcular") -> 10

Sheet Saídas
E1: Controle de Saídas
B4: Mês | C4: Data | D4: Produto | E4: Quantidade Vendida | F4: Preço Unitário | G4: Valor de Venda
B5: =MONTH(TB_Saídas[[#This Row],[Data]]) -> 1 | C5: 44566 | D5: Coxinha | E5: 30 | F5: {=_xlfn.XLOOKUP(TB_Saídas[[#This Row],[Produto]],TB_Produtos[[#All],[Produto]],TB_Produtos[[#All],[Preço Unitário]],"Produto não Encontrado",0,1)} -> 6.5 | G5: =IFERROR(TB_Saídas[[#This Row],[Quantidade Vendida]]*TB_Saídas[[#This Row],[Preço Unitário]],"Não foi possível calcular") -> 195
B6: =MONTH(TB_Saídas[[#This Row],[Data]]) -> 1 | C6: 44567 | D6: Café | E6: 80 | F6: {=_xlfn.XLOOKUP(TB_Saídas[[#This Row],[Produto]],TB_Produtos[[#All],[Produto]],TB_Produtos[[#All],[Preço Unitário]],"Produto não Encontrado",0,1)} -> 6 | G6: =IFERROR(TB_Saídas[[#This Row],[Quantidade Vendida]]*TB_Saídas[[#This Row],[Preço Unitário]],"Não foi possível calcular") -> 480
B7: =MONTH(TB_Saídas[[#This Row],[Data]]) -> 1 | C7: 44581 | D7: Pão de Queijo | E7: 50 | F7: {=_xlfn.XLOOKUP(TB_Saídas[[#This Row],[Produto]],TB_Produtos[[#All],[Produto]],TB_Produtos[[#All],[Preço Unitário]],"Produto não Encontrado",0,1)} -> 7.5 | G7: =IFERROR(TB_Saídas[[#This Row],[Quantidade Vendida]]*TB_Saídas[[#This Row],[Preço Unitário]],"Não foi possível calcular") -> 375
B8: =MONTH(TB_Saídas[[#This Row],[Data]]) -> 1 | C8: 44586 | D8: Chocolate Quente | E8: 50 | F8: {=_xlfn.XLOOKUP(TB_Saídas[[#This Row],[Produto]],TB_Produtos[[#All],[Produto]],TB_Produtos[[#All],[Preço Unitário]],"Produto não Encontrado",0,1)} -> 8.5 | G8: =IFERROR(TB_Saídas[[#This Row],[Quantidade Vendida]]*TB_Saídas[[#This Row],[Preço Unitário]],"Não foi possível calcular") -> 425
B9: =MONTH(TB_Saídas[[#This Row],[Data]]) -> 2 | C9: 44597 | D9: Pão de Queijo | E9: 30 | F9: {=_xlfn.XLOOKUP(TB_Saídas[[#This Row],[Produto]],TB_Produtos[[#All],[Produto]],TB_Produtos[[#All],[Preço Unitário]],"Produto não Encontrado",0,1)} -> 7.5 | G9: =IFERROR(TB_Saídas[[#This Row],[Quantidade Vendida]]*TB_Saídas[[#This Row],[Preço Unitário]],"Não foi possível calcular") -> 225
B10: =MONTH(TB_Saídas[[#This Row],[Data]]) -> 2 | C10: 44598 | D10: Café | E10: 110 | F10: {=_xlfn.XLOOKUP(TB_Saídas[[#This Row],[Produto]],TB_Produtos[[#All],[Produto]],TB_Produtos[[#All],[Preço Unitário]],"Produto não Encontrado",0,1)} -> 6 | G10: =IFERROR(TB_Saídas[[#This Row],[Quantidade Vendida]]*TB_Saídas[[#This Row],[Preço Unitário]],"Não foi possível calcular") -> 660
B11: =MONTH(TB_Saídas[[#This Row],[Data]]) -> 2 | C11: 44602 | D11: Chocolate Quente | E11: 75 | F11: {=_xlfn.XLOOKUP(TB_Saídas[[#This Row],[Produto]],TB_Produtos[[#All],[Produto]],TB_Produtos[[#All],[Preço Unitário]],"Produto não Encontrado",0,1)} -> 8.5 | G11: =IFERROR(TB_Saídas[[#This Row],[Quantidade Vendida]]*TB_Saídas[[#This Row],[Preço Unitário]],"Não foi possível calcular") -> 637.5
B12: =MONTH(TB_Saídas[[#This Row],[Data]]) -> 2 | C12: 44620 | D12: Coxinha | E12: 20 | F12: {=_xlfn.XLOOKUP(TB_Saídas[[#This Row],[Produto]],TB_Produtos[[#All],[Produto]],TB_Produtos[[#All],[Preço Unitário]],"Produto não Encontrado",0,1)} -> 6.5 | G12: =IFERROR(TB_Saídas[[#This Row],[Quantidade Vendida]]*TB_Saídas[[#This Row],[Preço Unitário]],"Não foi possível calcular") -> 130
B13: =MONTH(TB_Saídas[[#This Row],[Data]]) -> 3 | C13: 44626 | D13: Refrigerante | E13: 110 | F13: {=_xlfn.XLOOKUP(TB_Saídas[[#This Row],[Produto]],TB_Produtos[[#All],[Produto]],TB_Produtos[[#All],[Preço Unitário]],"Produto não Encontrado",0,1)} -> 8 | G13: =IFERROR(TB_Saídas[[#This Row],[Quantidade Vendida]]*TB_Saídas[[#This Row],[Preço Unitário]],"Não foi possível calcular") -> 880
B14: =MONTH(TB_Saídas[[#This Row],[Data]]) -> 3 | C14: 44631 | D14: Pão de Queijo | E14: 40 | F14: {=_xlfn.XLOOKUP(TB_Saídas[[#This Row],[Produto]],TB_Produtos[[#All],[Produto]],TB_Produtos[[#All],[Preço Unitário]],"Produto não Encontrado",0,1)} -> 7.5 | G14: =IFERROR(TB_Saídas[[#This Row],[Quantidade Vendida]]*TB_Saídas[[#This Row],[Preço Unitário]],"Não foi possível calcular") -> 300
B15: =MONTH(TB_Saídas[[#This Row],[Data]]) -> 3 | C15: 44646 | D15: Chocolate Quente | E15: 50 | F15: {=_xlfn.XLOOKUP(TB_Saídas[[#This Row],[Produto]],TB_Produtos[[#All],[Produto]],TB_Produtos[[#All],[Preço Unitário]],"Produto não Encontrado",0,1)} -> 8.5 | G15: =IFERROR(TB_Saídas[[#This Row],[Quantidade Vendida]]*TB_Saídas[[#This Row],[Preço Unitário]],"Não foi possível calcular") -> 425
B16: =MONTH(TB_Saídas[[#This Row],[Data]]) -> 3 | C16: 44649 | D16: Coxinha | E16: 15 | F16: {=_xlfn.XLOOKUP(TB_Saídas[[#This Row],[Produto]],TB_Produtos[[#All],[Produto]],TB_Produtos[[#All],[Preço Unitário]],"Produto não Encontrado",0,1)} -> 6.5 | G16: =IFERROR(TB_Saídas[[#This Row],[Quantidade Vendida]]*TB_Saídas[[#This Row],[Preço Unitário]],"Não foi possível calcular") -> 97.5
... B61: =MONTH(TB_Saídas[[#This Row],[Data]]) -> 12 | C61: 44917 | D61: Chocolate Quente | E61: 23 | F61: {=_xlfn.XLOOKUP(TB_Saídas[[#This Row],[Produto]],TB_Produtos[[#All],[Produto]],TB_Produtos[[#All],[Preço Unitário]],"Produto não Encontrado",0,1)} -> 8.5 | G61: =IFERROR(TB_Saídas[[#This Row],[Quantidade Vendida]]*TB_Saídas[[#This Row],[Preço Unitário]],"Não foi possível calcular") -> 195.5

Sheet Base de Cálculos
A1: Top 5 Mais Vendidos | F1: Faturamento Vs Despesas | K1: Produto: | L1: Entradas e Saídas (Qtd) | P1: Entradas vs Saídas
B2: Produto | C2: Entradas | D2: Saídas | F2: N. Mês | G2: Mês | H2: Faturamento | I2: Despesas | K2: =Dashboard!AN30 -> Café | L2: Mês | M2: Entradas | N2: Saídas | P2: Entradas | Q2: =SUM(M3:M14) -> 1635
A3: 1 | B3: =_xlfn.XLOOKUP(D3,'Visão Produtos'!B:B,'Visão Produtos'!A:A) -> Café | C3: =SUMIF(TB_Entradas[Produto],B3,TB_Entradas[Quantidade Comprada]) -> 1635 | D3: =LARGE('Visão Produtos'!B:B,'Base de Cálculos'!A3) -> 945 | F3: 1 | G3: Jan | H3: =SUMIF(TB_Saídas[Mês],F3,TB_Saídas[Valor de Venda]) -> 1475 | I3: =SUMIF(TB_Entradas[Mês],F3,TB_Entradas[Valor da Compra]) -> 297.5 | L3: Jan | M3: =SUMIFS(TB_Entradas[Quantidade Comprada],TB_Entradas[Produto],$K$2,TB_Entradas[Mês],$F3) -> 100 | N3: =SUMIFS(TB_Saídas[Quantidade Vendida],TB_Saídas[Produto],$K$2,TB_Saídas[Mês],$F3) -> 80 | P3: Saídas | Q3: =SUM(N3:N14) -> 945
A4: 2 | B4: =_xlfn.XLOOKUP(D4,'Visão Produtos'!B:B,'Visão Produtos'!A:A) -> Chocolate Quente | C4: =SUMIF(TB_Entradas[Produto],B4,TB_Entradas[Quantidade Comprada]) -> 750 | D4: =LARGE('Visão Produtos'!B:B,'Base de Cálculos'!A4) -> 500 | F4: 2 | G4: Fev | H4: =SUMIF(TB_Saídas[Mês],F4,TB_Saídas[Valor de Venda]) -> 1652.5 | I4: =SUMIF(TB_Entradas[Mês],F4,TB_Entradas[Valor da Compra]) -> 378.75 | L4: Fev | M4: =SUMIFS(TB_Entradas[Quantidade Comprada],TB_Entradas[Produto],$K$2,TB_Entradas[Mês],$F4) -> 125 | N4: =SUMIFS(TB_Saídas[Quantidade Vendida],TB_Saídas[Produto],$K$2,TB_Saídas[Mês],$F4) -> 110
A5: 3 | B5: =_xlfn.XLOOKUP(D5,'Visão Produtos'!B:B,'Visão Produtos'!A:A) -> Pão de Queijo | C5: =SUMIF(TB_Entradas[Produto],B5,TB_Entradas[Quantidade Comprada]) -> 620 | D5: =LARGE('Visão Produtos'!B:B,'Base de Cálculos'!A5) -> 400 | F5: 3 | G5: Mar | H5: =SUMIF(TB_Saídas[Mês],F5,TB_Saídas[Valor de Venda]) -> 2302.5 | I5: =SUMIF(TB_Entradas[Mês],F5,TB_Entradas[Valor da Compra]) -> 922.5 | L5: Mar | M5: =SUMIFS(TB_Entradas[Quantidade Comprada],TB_Entradas[Produto],$K$2,TB_Entradas[Mês],$F5) -> 150 | N5: =SUMIFS(TB_Saídas[Quantidade Vendida],TB_Saídas[Produto],$K$2,TB_Saídas[Mês],$F5) -> 100
A6: 4 | B6: =_xlfn.XLOOKUP(D6,'Visão Produtos'!B:B,'Visão Produtos'!A:A) -> Coxinha | C6: =SUMIF(TB_Entradas[Produto],B6,TB_Entradas[Quantidade Comprada]) -> 550 | D6: =LARGE('Visão Produtos'!B:B,'Base de Cálculos'!A6) -> 245 | F6: 4 | G6: Abr | H6: =SUMIF(TB_Saídas[Mês],F6,TB_Saídas[Valor de Venda]) -> 1507.5 | I6: =SUMIF(TB_Entradas[Mês],F6,TB_Entradas[Valor da Compra]) -> 362.5 | L6: Abr | M6: =SUMIFS(TB_Entradas[Quantidade Comprada],TB_Entradas[Produto],$K$2,TB_Entradas[Mês],$F6) -> 150 | N6: =SUMIFS(TB_Saídas[Quantidade Vendida],TB_Saídas[Produto],$K$2,TB_Saídas[Mês],$F6) -> 75
A7: 5 | B7: =_xlfn.XLOOKUP(D7,'Visão Produtos'!B:B,'Visão Produtos'!A:A) -> Refrigerante | C7: =SUMIF(TB_Entradas[Produto],B7,TB_Entradas[Quantidade Comprada]) -> 350 | D7: =LARGE('Visão Produtos'!B:B,'Base de Cálculos'!A7) -> 210 | F7: 5 | G7: Mai | H7: =SUMIF(TB_Saídas[Mês],F7,TB_Saídas[Valor de Venda]) -> 1372 | I7: =SUMIF(TB_Entradas[Mês],F7,TB_Entradas[Valor da Compra]) -> 723.75 | L7: Mai | M7: =SUMIFS(TB_Entradas[Quantidade Comprada],TB_Entradas[Produto],$K$2,TB_Entradas[Mês],$F7) -> 100 | N7: =SUMIFS(TB_Saídas[Quantidade Vendida],TB_Saídas[Produto],$K$2,TB_Saídas[Mês],$F7) -> 75
F8: 6 | G8: Jun | H8: =SUMIF(TB_Saídas[Mês],F8,TB_Saídas[Valor de Venda]) -> 1145 | I8: =SUMIF(TB_Entradas[Mês],F8,TB_Entradas[Valor da Compra]) -> 376.25 | L8: Jun | M8: =SUMIFS(TB_Entradas[Quantidade Comprada],TB_Entradas[Produto],$K$2,TB_Entradas[Mês],$F8) -> 150 | N8: =SUMIFS(TB_Saídas[Quantidade Vendida],TB_Saídas[Produto],$K$2,TB_Saídas[Mês],$F8) -> 100
A9: Top 5 Maiores Faturamentos | F9: 7 | G9: Jul | H9: =SUMIF(TB_Saídas[Mês],F9,TB_Saídas[Valor de Venda]) -> 2217.5 | I9: =SUMIF(TB_Entradas[Mês],F9,TB_Entradas[Valor da Compra]) -> 355 | L9: Jul | M9: =SUMIFS(TB_Entradas[Quantidade Comprada],TB_Entradas[Produto],$K$2,TB_Entradas[Mês],$F9) -> 150 | N9: =SUMIFS(TB_Saídas[Quantidade Vendida],TB_Saídas[Produto],$K$2,TB_Saídas[Mês],$F9) -> 90
B10: Produto | C10: Faturamento | F10: 8 | G10: Ago | H10: =SUMIF(TB_Saídas[Mês],F10,TB_Saídas[Valor de Venda]) -> 1621.5 | I10: =SUMIF(TB_Entradas[Mês],F10,TB_Entradas[Valor da Compra]) -> 431.25 | L10: Ago | M10: =SUMIFS(TB_Entradas[Quantidade Comprada],TB_Entradas[Produto],$K$2,TB_Entradas[Mês],$F10) -> 150 | N10: =SUMIFS(TB_Saídas[Quantidade Vendida],TB_Saídas[Produto],$K$2,TB_Saídas[Mês],$F10) -> 100
A11: 1 | B11: =_xlfn.XLOOKUP(C11,'Visão Produtos'!C:C,'Visão Produtos'!A:A) -> Café | C11: =LARGE('Visão Produtos'!C:C,'Base de Cálculos'!A11) -> 5670 | F11: 9 | G11: Set | H11: =SUMIF(TB_Saídas[Mês],F11,TB_Saídas[Valor de Venda]) -> 2234 | I11: =SUMIF(TB_Entradas[Mês],F11,TB_Entradas[Valor da Compra]) -> 806 | L11: Set | M11: =SUMIFS(TB_Entradas[Quantidade Comprada],TB_Entradas[Produto],$K$2,TB_Entradas[Mês],$F11) -> 180 | N11: =SUMIFS(TB_Saídas[Quantidade Vendida],TB_Saídas[Produto],$K$2,TB_Saídas[Mês],$F11) -> 35
A12: 2 | B12: =_xlfn.XLOOKUP(C12,'Visão Produtos'!C:C,'Visão Produtos'!A:A) -> Chocolate Quente | C12: =LARGE('Visão Produtos'!C:C,'Base de Cálculos'!A12) -> 4250 | F12: 10 | G12: Out | H12: =SUMIF(TB_Saídas[Mês],F12,TB_Saídas[Valor de Venda]) -> 1508 | I12: =SUMIF(TB_Entradas[Mês],F12,TB_Entradas[Valor da Compra]) -> 247.75 | L12: Out | M12: =SUMIFS(TB_Entradas[Quantidade Comprada],TB_Entradas[Produto],$K$2,TB_Entradas[Mês],$F12) -> 100 | N12: =SUMIFS(TB_Saídas[Quantidade Vendida],TB_Saídas[Produto],$K$2,TB_Saídas[Mês],$F12) -> 30
A13: 3 | B13: =_xlfn.XLOOKUP(C13,'Visão Produtos'!C:C,'Visão Produtos'!A:A) -> Pão de Queijo | C13: =LARGE('Visão Produtos'!C:C,'Base de Cálculos'!A13) -> 3000 | F13: 11 | G13: Nov | H13: =SUMIF(TB_Saídas[Mês],F13,TB_Saídas[Valor de Venda]) -> 811.5 | I13: =SUMIF(TB_Entradas[Mês],F13,TB_Entradas[Valor da Compra]) -> 218.75 | L13: Nov | M13: =SUMIFS(TB_Entradas[Quantidade Comprada],TB_Entradas[Produto],$K$2,TB_Entradas[Mês],$F13) -> 80 | N13: =SUMIFS(TB_Saídas[Quantidade Vendida],TB_Saídas[Produto],$K$2,TB_Saídas[Mês],$F13) -> 50
A14: 4 | B14: =_xlfn.XLOOKUP(C14,'Visão Produtos'!C:C,'Visão Produtos'!A:A) -> Refrigerante | C14: =LARGE('Visão Produtos'!C:C,'Base de Cálculos'!A14) -> 1680 | F14: 12 | G14: Dez | H14: =SUMIF(TB_Saídas[Mês],F14,TB_Saídas[Valor de Venda]) -> 1195.5 | I14: =SUMIF(TB_Entradas[Mês],F14,TB_Entradas[Valor da Compra]) -> 410 | L14: Dez | M14: =SUMIFS(TB_Entradas[Quantidade Comprada],TB_Entradas[Produto],$K$2,TB_Entradas[Mês],$F14) -> 200 | N14: =SUMIFS(TB_Saídas[Quantidade Vendida],TB_Saídas[Produto],$K$2,TB_Saídas[Mês],$F14) -> 100
A15: 5 | B15: =_xlfn.XLOOKUP(C15,'Visão Produtos'!C:C,'Visão Produtos'!A:A) -> Coxinha | C15: =LARGE('Visão Produtos'!C:C,'Base de Cálculos'!A15) -> 1592.5 | L15: Total | M15: =SUM(M2:M14) -> 1635 | N15: =SUM(N2:N14) -> 945

Sheet Visão Produtos
A1: {=TB_Produtos[Produto]} -> Café | B1: =SUMIF(TB_Saídas[Produto],A1,TB_Saídas[Quantidade Vendida]) -> 945 | C1: =SUMIF(TB_Saídas[Produto],A1,TB_Saídas[Valor de Venda]) -> 5670
A2: Pão | B2: =SUMIF(TB_Saídas[Produto],A2,TB_Saídas[Quantidade Vendida]) -> 0 | C2: =SUMIF(TB_Saídas[Produto],A2,TB_Saídas[Valor de Venda]) -> 0
A3: Coxinha | B3: =SUMIF(TB_Saídas[Produto],A3,TB_Saídas[Quantidade Vendida]) -> 245 | C3: =SUMIF(TB_Saídas[Produto],A3,TB_Saídas[Valor de Venda]) -> 1592.5
A4: Esfiha | B4: =SUMIF(TB_Saídas[Produto],A4,TB_Saídas[Quantidade Vendida]) -> 0 | C4: =SUMIF(TB_Saídas[Produto],A4,TB_Saídas[Valor de Venda]) -> 0
A5: Risoles | B5: =SUMIF(TB_Saídas[Produto],A5,TB_Saídas[Quantidade Vendida]) -> 0 | C5: =SUMIF(TB_Saídas[Produto],A5,TB_Saídas[Valor de Venda]) -> 0
A6: Empada | B6: =SUMIF(TB_Saídas[Produto],A6,TB_Saídas[Quantidade Vendida]) -> 0 | C6: =SUMIF(TB_Saídas[Produto],A6,TB_Saídas[Valor de Venda]) -> 0
A7: Quibe | B7: =SUMIF(TB_Saídas[Produto],A7,TB_Saídas[Quantidade Vendida]) -> 0 | C7: =SUMIF(TB_Saídas[Produto],A7,TB_Saídas[Valor de Venda]) -> 0
A8: Chá | B8: =SUMIF(TB_Saídas[Produto],A8,TB_Saídas[Quantidade Vendida]) -> 0 | C8: =SUMIF(TB_Saídas[Produto],A8,TB_Saídas[Valor de Venda]) -> 0
A9: Manteiga | B9: =SUMIF(TB_Saídas[Produto],A9,TB_Saídas[Quantidade Vendida]) -> 0 | C9: =SUMIF(TB_Saídas[Produto],A9,TB_Saídas[Valor de Venda]) -> 0
A10: Requeijão | B10: =SUMIF(TB_Saídas[Produto],A10,TB_Saídas[Quantidade Vendida]) -> 0 | C10: =SUMIF(TB_Saídas[Produto],A10,TB_Saídas[Valor de Venda]) -> 0
A11: Chocolate Quente | B11: =SUMIF(TB_Saídas[Produto],A11,TB_Saídas[Quantidade Vendida]) -> 500 | C11: =SUMIF(TB_Saídas[Produto],A11,TB_Saídas[Valor de Venda]) -> 4250
A12: Leite | B12: =SUMIF(TB_Saídas[Produto],A12,TB_Saídas[Quantidade Vendida]) -> 0 | C12: =SUMIF(TB_Saídas[Produto],A12,TB_Saídas[Valor de Venda]) -> 0
A13: Açúcar | B13: =SUMIF(TB_Saídas[Produto],A13,TB_Saídas[Quantidade Vendida]) -> 0 | C13: =SUMIF(TB_Saídas[Produto],A13,TB_Saídas[Valor de Venda]) -> 0
... A27: Enroladinho | B27: =SUMIF(TB_Saídas[Produto],A27,TB_Saídas[Quantidade Vendida]) -> 0 | C27: =SUMIF(TB_Saídas[Produto],A27,TB_Saídas[Valor de Venda]) -> 0
B28: =SUMIF(TB_Saídas[Produto],A28,TB_Saídas[Quantidade Vendida]) -> 0 | C28: =SUMIF(TB_Saídas[Produto],A28,TB_Saídas[Valor de Venda]) -> 0
B29: =SUMIF(TB_Saídas[Produto],A29,TB_Saídas[Quantidade Vendida]) -> 0 | C29: =SUMIF(TB_Saídas[Produto],A29,TB_Saídas[Valor de Venda]) -> 0
B30: =SUMIF(TB_Saídas[Produto],A30,TB_Saídas[Quantidade Vendida]) -> 0 | C30: =SUMIF(TB_Saídas[Produto],A30,TB_Saídas[Valor de Venda]) -> 0
B31: =SUMIF(TB_Saídas[Produto],A31,TB_Saídas[Quantidade Vendida]) -> 0 | C31: =SUMIF(TB_Saídas[Produto],A31,TB_Saídas[Valor de Venda]) -> 0
B32: =SUMIF(TB_Saídas[Produto],A32,TB_Saídas[Quantidade Vendida]) -> 0 | C32: =SUMIF(TB_Saídas[Produto],A32,TB_Saídas[Valor de Venda]) -> 0
B33: =SUMIF(TB_Saídas[Produto],A33,TB_Saídas[Quantidade Vendida]) -> 0 | C33: =SUMIF(TB_Saídas[Produto],A33,TB_Saídas[Valor de Venda]) -> 0
B34: =SUMIF(TB_Saídas[Produto],A34,TB_Saídas[Quantidade Vendida]) -> 0 | C34: =SUMIF(TB_Saídas[Produto],A34,TB_Saídas[Valor de Venda]) -> 0
B35: =SUMIF(TB_Saídas[Produto],A35,TB_Saídas[Quantidade Vendida]) -> 0 | C35: =SUMIF(TB_Saídas[Produto],A35,TB_Saídas[Valor de Venda]) -> 0
B36: =SUMIF(TB_Saídas[Produto],A36,TB_Saídas[Quantidade Vendida]) -> 0 | C36: =SUMIF(TB_Saídas[Produto],A36,TB_Saídas[Valor de Venda]) -> 0
B37: =SUMIF(TB_Saídas[Produto],A37,TB_Saídas[Quantidade Vendida]) -> 0 | C37: =SUMIF(TB_Saídas[Produto],A37,TB_Saídas[Valor de Venda]) -> 0
B38: =SUMIF(TB_Saídas[Produto],A38,TB_Saídas[Quantidade Vendida]) -> 0 | C38: =SUMIF(TB_Saídas[Produto],A38,TB_Saídas[Valor de Venda]) -> 0
B39: =SUMIF(TB_Saídas[Produto],A39,TB_Saídas[Quantidade Vendida]) -> 0 | C39: =SUMIF(TB_Saídas[Produto],A39,TB_Saídas[Valor de Venda]) -> 0
... B200: =SUMIF(TB_Saídas[Produto],A200,TB_Saídas[Quantidade Vendida]) -> 0 | C200: =SUMIF(TB_Saídas[Produto],A200,TB_Saídas[Valor de Venda]) -> 0

Sheet Controle de Estoque
F1: Controle de Estoque
B5: Produto | C5: Entradas | D5: Saídas | E5: Saldo em Estoque | F5: Estoque Mínimo | G5: Status do Estoque | H5: Valor de Venda | I5: Custo Total | J5: Lucro
B6: Refrigerante | C6: =IFERROR(SUMIF(TB_Entradas[Produto],TB_ControleEstoque[[#This Row],[Produto]],TB_Entradas[Quantidade Comprada]),0) -> 350 | D6: =IFERROR(SUMIF(TB_Saídas[Produto],TB_ControleEstoque[[#This Row],[Produto]],TB_Saídas[Quantidade Vendida]),0) -> 210 | E6: =TB_ControleEstoque[[#This Row],[Entradas]]-TB_ControleEstoque[[#This Row],[Saídas ]] -> 140 | F6: =_xlfn.XLOOKUP(TB_ControleEstoque[[#This Row],[Produto]],TB_Produtos[Produto],TB_Produtos[Estoque Mínimo],"Erro",0,1) -> 10 | G6: {=_xlfn.IFS(TB_ControleEstoque[[#This Row],[Saldo em Estoque]]>TB_ControleEstoque[[#This Row],[Estoque Mínimo]],"Estoque OK",TB_ControleEstoque[[#This Row],[Saldo em Estoque]]=0,"Estoque Zerado",1,"Repor Estoque")} -> Estoque OK | H6: =SUMIFS(TB_Saídas[Valor de Venda],TB_Saídas[Produto],TB_ControleEstoque[[#This Row],[Produto]]) -> 1680 | I6: =SUMIFS(TB_Entradas[Valor da Compra],TB_Entradas[Produto],TB_ControleEstoque[[#This Row],[Produto]]) -> 700 | J6: =TB_ControleEstoque[[#This Row],[Valor de Venda]]-TB_ControleEstoque[[#This Row],[Custo Total]] -> 980
B7: Café | C7: =IFERROR(SUMIF(TB_Entradas[Produto],TB_ControleEstoque[[#This Row],[Produto]],TB_Entradas[Quantidade Comprada]),0) -> 1635 | D7: =IFERROR(SUMIF(TB_Saídas[Produto],TB_ControleEstoque[[#This Row],[Produto]],TB_Saídas[Quantidade Vendida]),0) -> 945 | E7: =TB_ControleEstoque[[#This Row],[Entradas]]-TB_ControleEstoque[[#This Row],[Saídas ]] -> 690 | F7: =_xlfn.XLOOKUP(TB_ControleEstoque[[#This Row],[Produto]],TB_Produtos[Produto],TB_Produtos[Estoque Mínimo],"Erro",0,1) -> 50 | G7: {=_xlfn.IFS(TB_ControleEstoque[[#This Row],[Saldo em Estoque]]>TB_ControleEstoque[[#This Row],[Estoque Mínimo]],"Estoque OK",TB_ControleEstoque[[#This Row],[Saldo em Estoque]]=0,"Estoque Zerado",1,"Repor Estoque")} -> Estoque OK | H7: =SUMIFS(TB_Saídas[Valor de Venda],TB_Saídas[Produto],TB_ControleEstoque[[#This Row],[Produto]]) -> 5670 | I7: =SUMIFS(TB_Entradas[Valor da Compra],TB_Entradas[Produto],TB_ControleEstoque[[#This Row],[Produto]]) -> 3270 | J7: =TB_ControleEstoque[[#This Row],[Valor de Venda]]-TB_ControleEstoque[[#This Row],[Custo Total]] -> 2400 | N7: Produto Mais Rentável
B8: Suco de Laranja | C8: =IFERROR(SUMIF(TB_Entradas[Produto],TB_ControleEstoque[[#This Row],[Produto]],TB_Entradas[Quantidade Comprada]),0) -> 100 | D8: =IFERROR(SUMIF(TB_Saídas[Produto],TB_ControleEstoque[[#This Row],[Produto]],TB_Saídas[Quantidade Vendida]),0) -> 100 | E8: =TB_ControleEstoque[[#This Row],[Entradas]]-TB_ControleEstoque[[#This Row],[Saídas ]] -> 0 | F8: =_xlfn.XLOOKUP(TB_ControleEstoque[[#This Row],[Produto]],TB_Produtos[Produto],TB_Produtos[Estoque Mínimo],"Erro",0,1) -> 5 | G8: {=_xlfn.IFS(TB_ControleEstoque[[#This Row],[Saldo em Estoque]]>TB_ControleEstoque[[#This Row],[Estoque Mínimo]],"Estoque OK",TB_ControleEstoque[[#This Row],[Saldo em Estoque]]=0,"Estoque Zerado",1,"Repor Estoque")} -> Estoque Zerado | H8: =SUMIFS(TB_Saídas[Valor de Venda],TB_Saídas[Produto],TB_ControleEstoque[[#This Row],[Produto]]) -> 1000 | I8: =SUMIFS(TB_Entradas[Valor da Compra],TB_Entradas[Produto],TB_ControleEstoque[[#This Row],[Produto]]) -> 75 | J8: =TB_ControleEstoque[[#This Row],[Valor de Venda]]-TB_ControleEstoque[[#This Row],[Custo Total]] -> 925 | N8: Lucro | P8: Produto
B9: Cerveja | C9: =IFERROR(SUMIF(TB_Entradas[Produto],TB_ControleEstoque[[#This Row],[Produto]],TB_Entradas[Quantidade Comprada]),0) -> 50 | D9: =IFERROR(SUMIF(TB_Saídas[Produto],TB_ControleEstoque[[#This Row],[Produto]],TB_Saídas[Quantidade Vendida]),0) -> 25 | E9: =TB_ControleEstoque[[#This Row],[Entradas]]-TB_ControleEstoque[[#This Row],[Saídas ]] -> 25 | F9: =_xlfn.XLOOKUP(TB_ControleEstoque[[#This Row],[Produto]],TB_Produtos[Produto],TB_Produtos[Estoque Mínimo],"Erro",0,1) -> 5 | G9: {=_xlfn.IFS(TB_ControleEstoque[[#This Row],[Saldo em Estoque]]>TB_ControleEstoque[[#This Row],[Estoque Mínimo]],"Estoque OK",TB_ControleEstoque[[#This Row],[Saldo em Estoque]]=0,"Estoque Zerado",1,"Repor Estoque")} -> Estoque OK | H9: =SUMIFS(TB_Saídas[Valor de Venda],TB_Saídas[Produto],TB_ControleEstoque[[#This Row],[Produto]]) -> 200 | I9: =SUMIFS(TB_Entradas[Valor da Compra],TB_Entradas[Produto],TB_ControleEstoque[[#This Row],[Produto]]) -> 37.5 | J9: =TB_ControleEstoque[[#This Row],[Valor de Venda]]-TB_ControleEstoque[[#This Row],[Custo Total]] -> 162.5 | N9: =LARGE(TB_ControleEstoque[Lucro],1) -> 4062.5 | P9: =DGET(TB_ControleEstoque[#All],1,N8:N9) -> Chocolate Quente
B10: Chocolate Quente | C10: =IFERROR(SUMIF(TB_Entradas[Produto],TB_ControleEstoque[[#This Row],[Produto]],TB_Entradas[Quantidade Comprada]),0) -> 750 | D10: =IFERROR(SUMIF(TB_Saídas[Produto],TB_ControleEstoque[[#This Row],[Produto]],TB_Saídas[Quantidade Vendida]),0) -> 500 | E10: =TB_ControleEstoque[[#This Row],[Entradas]]-TB_ControleEstoque[[#This Row],[Saídas ]] -> 250 | F10: =_xlfn.XLOOKUP(TB_ControleEstoque[[#This Row],[Produto]],TB_Produtos[Produto],TB_Produtos[Estoque Mínimo],"Erro",0,1) -> 10 | G10: {=_xlfn.IFS(TB_ControleEstoque[[#This Row],[Saldo em Estoque]]>TB_ControleEstoque[[#This Row],[Estoque Mínimo]],"Estoque OK",TB_ControleEstoque[[#This Row],[Saldo em Estoque]]=0,"Estoque Zerado",1,"Repor Estoque")} -> Estoque OK | H10: =SUMIFS(TB_Saídas[Valor de Venda],TB_Saídas[Produto],TB_ControleEstoque[[#This Row],[Produto]]) -> 4250 | I10: =SUMIFS(TB_Entradas[Valor da Compra],TB_Entradas[Produto],TB_ControleEstoque[[#This Row],[Produto]]) -> 187.5 | J10: =TB_ControleEstoque[[#This Row],[Valor de Venda]]-TB_ControleEstoque[[#This Row],[Custo Total]] -> 4062.5
B11: Pão de Queijo | C11: =IFERROR(SUMIF(TB_Entradas[Produto],TB_ControleEstoque[[#This Row],[Produto]],TB_Entradas[Quantidade Comprada]),0) -> 620 | D11: =IFERROR(SUMIF(TB_Saídas[Produto],TB_ControleEstoque[[#This Row],[Produto]],TB_Saídas[Quantidade Vendida]),0) -> 400 | E11: =TB_ControleEstoque[[#This Row],[Entradas]]-TB_ControleEstoque[[#This Row],[Saídas ]] -> 220 | F11: =_xlfn.XLOOKUP(TB_ControleEstoque[[#This Row],[Produto]],TB_Produtos[Produto],TB_Produtos[Estoque Mínimo],"Erro",0,1) -> 10 | G11: {=_xlfn.IFS(TB_ControleEstoque[[#This Row],[Saldo em Estoque]]>TB_ControleEstoque[[#This Row],[Estoque Mínimo]],"Estoque OK",TB_ControleEstoque[[#This Row],[Saldo em Estoque]]=0,"Estoque Zerado",1,"Repor Estoque")} -> Estoque OK | H11: =SUMIFS(TB_Saídas[Valor de Venda],TB_Saídas[Produto],TB_ControleEstoque[[#This Row],[Produto]]) -> 3000 | I11: =SUMIFS(TB_Entradas[Valor da Compra],TB_Entradas[Produto],TB_ControleEstoque[[#This Row],[Produto]]) -> 155 | J11: =TB_ControleEstoque[[#This Row],[Valor de Venda]]-TB_ControleEstoque[[#This Row],[Custo Total]] -> 2845
B12: Coxinha | C12: =IFERROR(SUMIF(TB_Entradas[Produto],TB_ControleEstoque[[#This Row],[Produto]],TB_Entradas[Quantidade Comprada]),0) -> 550 | D12: =IFERROR(SUMIF(TB_Saídas[Produto],TB_ControleEstoque[[#This Row],[Produto]],TB_Saídas[Quantidade Vendida]),0) -> 245 | E12: =TB_ControleEstoque[[#This Row],[Entradas]]-TB_ControleEstoque[[#This Row],[Saídas ]] -> 305 | F12: =_xlfn.XLOOKUP(TB_ControleEstoque[[#This Row],[Produto]],TB_Produtos[Produto],TB_Produtos[Estoque Mínimo],"Erro",0,1) -> 50 | G12: {=_xlfn.IFS(TB_ControleEstoque[[#This Row],[Saldo em Estoque]]>TB_ControleEstoque[[#This Row],[Estoque Mínimo]],"Estoque OK",TB_ControleEstoque[[#This Row],[Saldo em Estoque]]=0,"Estoque Zerado",1,"Repor Estoque")} -> Estoque OK | H12: =SUMIFS(TB_Saídas[Valor de Venda],TB_Saídas[Produto],TB_ControleEstoque[[#This Row],[Produto]]) -> 1592.5 | I12: =SUMIFS(TB_Entradas[Valor da Compra],TB_Entradas[Produto],TB_ControleEstoque[[#This Row],[Produto]]) -> 275 | J12: =TB_ControleEstoque[[#This Row],[Valor de Venda]]-TB_ControleEstoque[[#This Row],[Custo Total]] -> 1317.5
B13: Frango | C13: =IFERROR(SUMIF(TB_Entradas[Produto],TB_ControleEstoque[[#This Row],[Produto]],TB_Entradas[Quantidade Comprada]),0) -> 50 | D13: =IFERROR(SUMIF(TB_Saídas[Produto],TB_ControleEstoque[[#This Row],[Produto]],TB_Saídas[Quantidade Vendida]),0) -> 30 | E13: =TB_ControleEstoque[[#This Row],[Entradas]]-TB_ControleEstoque[[#This Row],[Saídas ]] -> 20 | F13: =_xlfn.XLOOKUP(TB_ControleEstoque[[#This Row],[Produto]],TB_Produtos[Produto],TB_Produtos[Estoque Mínimo],"Erro",0,1) -> 2 | G13: {=_xlfn.IFS(TB_ControleEstoque[[#This Row],[Saldo em Estoque]]>TB_ControleEstoque[[#This Row],[Estoque Mínimo]],"Estoque OK",TB_ControleEstoque[[#This Row],[Saldo em Estoque]]=0,"Estoque Zerado",1,"Repor Estoque")} -> Estoque OK | H13: =SUMIFS(TB_Saídas[Valor de Venda],TB_Saídas[Produto],TB_ControleEstoque[[#This Row],[Produto]]) -> 450 | I13: =SUMIFS(TB_Entradas[Valor da Compra],TB_Entradas[Produto],TB_ControleEstoque[[#This Row],[Produto]]) -> 225 | J13: =TB_ControleEstoque[[#This Row],[Valor de Venda]]-TB_ControleEstoque[[#This Row],[Custo Total]] -> 225
B14: Mini Pizza | C14: =IFERROR(SUMIF(TB_Entradas[Produto],TB_ControleEstoque[[#This Row],[Produto]],TB_Entradas[Quantidade Comprada]),0) -> 100 | D14: =IFERROR(SUMIF(TB_Saídas[Produto],TB_ControleEstoque[[#This Row],[Produto]],TB_Saídas[Quantidade Vendida]),0) -> 90 | E14: =TB_ControleEstoque[[#This Row],[Entradas]]-TB_ControleEstoque[[#This Row],[Saídas ]] -> 10 | F14: =_xlfn.XLOOKUP(TB_ControleEstoque[[#This Row],[Produto]],TB_Produtos[Produto],TB_Produtos[Estoque Mínimo],"Erro",0,1) -> 10 | G14: {=_xlfn.IFS(TB_ControleEstoque[[#This Row],[Saldo em Estoque]]>TB_ControleEstoque[[#This Row],[Estoque Mínimo]],"Estoque OK",TB_ControleEstoque[[#This Row],[Saldo em Estoque]]=0,"Estoque Zerado",1,"Repor Estoque")} -> Repor Estoque | H14: =SUMIFS(TB_Saídas[Valor de Venda],TB_Saídas[Produto],TB_ControleEstoque[[#This Row],[Produto]]) -> 450 | I14: =SUMIFS(TB_Entradas[Valor da Compra],TB_Entradas[Produto],TB_ControleEstoque[[#This Row],[Produto]]) -> 100 | J14: =TB_ControleEstoque[[#This Row],[Valor de Venda]]-TB_ControleEstoque[[#This Row],[Custo Total]] -> 350
B15: Hamburguer | C15: =IFERROR(SUMIF(TB_Entradas[Produto],TB_ControleEstoque[[#This Row],[Produto]],TB_Entradas[Quantidade Comprada]),0) -> 60 | D15: =IFERROR(SUMIF(TB_Saídas[Produto],TB_ControleEstoque[[#This Row],[Produto]],TB_Saídas[Quantidade Vendida]),0) -> 50 | E15: =TB_ControleEstoque[[#This Row],[Entradas]]-TB_ControleEstoque[[#This Row],[Saídas ]] -> 10 | F15: =_xlfn.XLOOKUP(TB_ControleEstoque[[#This Row],[Produto]],TB_Produtos[Produto],TB_Produtos[Estoque Mínimo],"Erro",0,1) -> 2 | G15: {=_xlfn.IFS(TB_ControleEstoque[[#This Row],[Saldo em Estoque]]>TB_ControleEstoque[[#This Row],[Estoque Mínimo]],"Estoque OK",TB_ControleEstoque[[#This Row],[Saldo em Estoque]]=0,"Estoque Zerado",1,"Repor Estoque")} -> Estoque OK | H15: =SUMIFS(TB_Saídas[Valor de Venda],TB_Saídas[Produto],TB_ControleEstoque[[#This Row],[Produto]]) -> 750 | I15: =SUMIFS(TB_Entradas[Valor da Compra],TB_Entradas[Produto],TB_ControleEstoque[[#This Row],[Produto]]) -> 480 | J15: =TB_ControleEstoque[[#This Row],[Valor de Venda]]-TB_ControleEstoque[[#This Row],[Custo Total]] -> 270

Sheet Consulta
G1: Consulta
D5: Data | F5: Produto
D6: <10/05/2022 | F6: ="=Café" -> =Café
D8: Quantidade Vendida | F8: =DSUM(TB_Saídas[#All],Consulta!D8,Consulta!D5:F6) -> 365
D10: Quantidade em Estoque | F10: =DSUM(TB_Entradas[#All],"Quantidade Comprada",Consulta!D5:F6)-F8 -> 160
D12: Valor da Compra | F12: =DSUM(TB_Entradas[#All],Consulta!D12,Consulta!D5:F6) -> 1050
D14: Valor de Venda | F14: =DSUM(TB_Saídas[#All],Consulta!D14,Consulta!D5:F6) -> 2190

Sheet Quadro de Resumo
AD1: Quadro de Resumo
C5: Dados 2022 | AB5: Consulta por Produto
AM7: Produto
D8: Produtos Vendidos: | N8: =COUNTA(_xlfn.UNIQUE(TB_Saídas[Produto])) -> 10 | AC8: Dados: | AM8: Café
D11: Qtd em Estoque: | N11: =SUM(TB_ControleEstoque[Saldo em Estoque]) -> 1670 | AC11: Qtd em Estoque: | AM11: =DSUM(TB_ControleEstoque[#All],TB_ControleEstoque[[#Headers],[Saldo em Estoque]],CriteriosConsultaProduto) -> 690
D14: Faturamento: | N14: =SUM(TB_Saídas[Valor de Venda]) -> 19042.5 | AC14: Faturamento: | AM14: =DSUM(TB_Saídas[#All],TB_Saídas[[#Headers],[Valor de Venda]],CriteriosConsultaProduto) -> 5670
D17: Despesas: | N17: =SUM(TB_Entradas[Valor da Compra]) -> 5530 | AC17: Despesas: | AM17: =DSUM(TB_Entradas[#All],TB_Entradas[[#Headers],[Valor da Compra]],CriteriosConsultaProduto) -> 3270
D20: Lucro: | N20: =N14-N17 -> 13512.5 | AC20: Lucro: | AM20: =AM14-AM17 -> 2400
D23: % Lucro: | N23: =N20/N17 -> 2.4434901 | AC23: % Lucro: | AM23: =AM20/AM17 -> 0.73394495
